<?xml version="1.0" encoding="UTF-8" standalone="yes"?><mets:eraldisEsitamineRequest xmlns:mets="http://metsaregister.x-road.eu" xmlns:xlink="http://www.w3.org/1999/xlink" xmlns:smil20lang="http://www.w3.org/2001/SMIL20/Language" xmlns:smil20="http://www.w3.org/2001/SMIL20/" xmlns:gml="http://www.opengis.net/gml" xmlns:xmime="http://www.w3.org/2005/05/xmlmime"><mets:ettevote>10880674</mets:ettevote><mets:yksused><mets:yksus><mets:kinnistuNimi>21573450</mets:kinnistuNimi><mets:kinnistuNr>21573450</mets:kinnistuNr><mets:eraldised><mets:eraldis><mets:katastriNr>71401:001:1256</mets:katastriNr><mets:eraldiseNr>3</mets:eraldiseNr><mets:inventKuup>2018-12-10+02:00</mets:inventKuup><mets:vKood>714</mets:vKood><mets:mKood>74</mets:mKood><mets:takseerija>38403194211</mets:takseerija><mets:pindala>0.6</mets:pindala><mets:kuivendatud>0</mets:kuivendatud><mets:kasvukoht>KL</mets:kasvukoht><mets:peapuuliik>MA</mets:peapuuliik><mets:korgusIndeks>18.2</mets:korgusIndeks><mets:boniteet>4</mets:boniteet><mets:tuleohuklass>1</mets:tuleohuklass><mets:arenguklass>K</mets:arenguklass><mets:kkVanus>72</mets:kkVanus><mets:kkRaievanus>110</mets:kkRaievanus><mets:juurdekasv>3.5</mets:juurdekasv><mets:rPindala1>17.9</mets:rPindala1><mets:taius1>58</mets:taius1><mets:tagavara1Ha>131</mets:tagavara1Ha><mets:tagavaraYHa>0</mets:tagavaraYHa><mets:geomeetria srsName="EPSG:3301"><gml:polygonMember xlink:type="simple"><gml:Polygon><gml:outerBoundaryIs><gml:LinearRing><gml:coordinates>394994.375048018,6487033.10541683 394940.97,6486998.44 394926.09,6486962.5 394898.11,6486955.59 394907.28,6487052.97 394972.53273403,6487073.70642401 394994.375048018,6487033.10541683</gml:coordinates></gml:LinearRing></gml:outerBoundaryIs></gml:Polygon></gml:polygonMember></mets:geomeetria><mets:elemendid><mets:element><mets:rinne>1</mets:rinne><mets:puuliik>MA</mets:puuliik><mets:paritolu>S</mets:paritolu><mets:osakaal>100</mets:osakaal><mets:vanus>65</mets:vanus><mets:synniaasta>1953</mets:synniaasta><mets:korgus>14.0</mets:korgus><mets:diameeter>20</mets:diameeter><mets:rinnaspindala>17.9</mets:rinnaspindala><mets:tagavara>131</mets:tagavara><mets:arv>569</mets:arv><mets:enamus>1</mets:enamus></mets:element></mets:elemendid><mets:isearasused><mets:isearasus>AO</mets:isearasus></mets:isearasused><mets:tood><mets:too><mets:too>HR</mets:too><mets:jarjekord>8</mets:jarjekord><mets:tooAasta>2018</mets:tooAasta></mets:too></mets:tood></mets:eraldis><mets:eraldis><mets:katastriNr>71401:001:1256</mets:katastriNr><mets:eraldiseNr>4</mets:eraldiseNr><mets:inventKuup>2018-12-10+02:00</mets:inventKuup><mets:vKood>714</mets:vKood><mets:mKood>74</mets:mKood><mets:takseerija>38403194211</mets:takseerija><mets:pindala>0.78</mets:pindala><mets:kuivendatud>0</mets:kuivendatud><mets:kasvukoht>KL</mets:kasvukoht><mets:peapuuliik>MA</mets:peapuuliik><mets:korgusIndeks>20.5</mets:korgusIndeks><mets:boniteet>3</mets:boniteet><mets:tuleohuklass>1</mets:tuleohuklass><mets:arenguklass>K</mets:arenguklass><mets:kkVanus>67</mets:kkVanus><mets:kkRaievanus>100</mets:kkRaievanus><mets:juurdekasv>4.1</mets:juurdekasv><mets:rPindala1>18.0</mets:rPindala1><mets:taius1>57</mets:taius1><mets:tagavara1Ha>138</mets:tagavara1Ha><mets:tagavaraYHa>0</mets:tagavaraYHa><mets:geomeetria srsName="EPSG:3301"><gml:polygonMember xlink:type="simple"><gml:Polygon><gml:outerBoundaryIs><gml:LinearRing><gml:coordinates>394893.027827096,6486901.61095374 394898.11,6486955.59 394926.09,6486962.5 394940.97,6486998.44 394994.619749653,6487033.26425358 395036.198006127,6486953.50722072 394988.49,6486957.49 394973.23,6486949.35 394928.51,6486925.48 394921.688186505,6486899.9680032 394893.027827096,6486901.61095374</gml:coordinates></gml:LinearRing></gml:outerBoundaryIs></gml:Polygon></gml:polygonMember></mets:geomeetria><mets:elemendid><mets:element><mets:rinne>1</mets:rinne><mets:puuliik>MA</mets:puuliik><mets:paritolu>S</mets:paritolu><mets:osakaal>100</mets:osakaal><mets:vanus>60</mets:vanus><mets:synniaasta>1958</mets:synniaasta><mets:korgus>15.0</mets:korgus><mets:diameeter>20</mets:diameeter><mets:rinnaspindala>18.0</mets:rinnaspindala><mets:tagavara>138</mets:tagavara><mets:arv>573</mets:arv><mets:enamus>1</mets:enamus></mets:element></mets:elemendid><mets:isearasused><mets:isearasus>AO</mets:isearasus></mets:isearasused><mets:tood><mets:too><mets:too>HR</mets:too><mets:jarjekord>8</mets:jarjekord><mets:tooAasta>2018</mets:tooAasta></mets:too></mets:tood></mets:eraldis><mets:eraldis><mets:katastriNr>71401:001:1256</mets:katastriNr><mets:eraldiseNr>5</mets:eraldiseNr><mets:inventKuup>2018-12-10+02:00</mets:inventKuup><mets:vKood>714</mets:vKood><mets:mKood>74</mets:mKood><mets:takseerija>38403194211</mets:takseerija><mets:pindala>0.37</mets:pindala><mets:kuivendatud>0</mets:kuivendatud><mets:kasvukoht>KL</mets:kasvukoht><mets:peapuuliik>MA</mets:peapuuliik><mets:korgusIndeks>17.0</mets:korgusIndeks><mets:boniteet>4</mets:boniteet><mets:tuleohuklass>1</mets:tuleohuklass><mets:arenguklass>V</mets:arenguklass><mets:kkVanus>107</mets:kkVanus><mets:kkRaievanus>110</mets:kkRaievanus><mets:juurdekasv>2.3</mets:juurdekasv><mets:rPindala1>20.1</mets:rPindala1><mets:taius1>61</mets:taius1><mets:tagavara1Ha>170</mets:tagavara1Ha><mets:tagavaraYHa>0</mets:tagavaraYHa><mets:jPuudeArv>500</mets:jPuudeArv><mets:geomeetria srsName="EPSG:3301"><gml:polygonMember xlink:type="simple"><gml:Polygon><gml:outerBoundaryIs><gml:LinearRing><gml:coordinates>394922.0073759442,6486901.161697505 394928.51,6486925.48 394973.23,6486949.35 395007.7,6486926.37 395030.83,6486917.48 395025.2508742843,6486894.980463851 394922.0073759442,6486901.161697505</gml:coordinates></gml:LinearRing></gml:outerBoundaryIs></gml:Polygon></gml:polygonMember></mets:geomeetria><mets:elemendid><mets:element><mets:rinne>1</mets:rinne><mets:puuliik>MA</mets:puuliik><mets:paritolu>S</mets:paritolu><mets:osakaal>100</mets:osakaal><mets:vanus>100</mets:vanus><mets:synniaasta>1918</mets:synniaasta><mets:korgus>17.0</mets:korgus><mets:diameeter>26</mets:diameeter><mets:rinnaspindala>20.1</mets:rinnaspindala><mets:tagavara>170</mets:tagavara><mets:arv>378</mets:arv><mets:enamus>1</mets:enamus></mets:element><mets:element><mets:rinne>J</mets:rinne><mets:puuliik>KU</mets:puuliik><mets:paritolu>S</mets:paritolu><mets:osakaal>100</mets:osakaal><mets:vanus>20</mets:vanus><mets:synniaasta>1998</mets:synniaasta><mets:korgus>1.0</mets:korgus><mets:rinnaspindala>0.0</mets:rinnaspindala><mets:arv>500</mets:arv><mets:enamus>0</mets:enamus></mets:element></mets:elemendid><mets:isearasused><mets:isearasus>AO</mets:isearasus></mets:isearasused><mets:tood><mets:too><mets:too>HR</mets:too><mets:jarjekord>8</mets:jarjekord><mets:tooAasta>2018</mets:tooAasta></mets:too></mets:tood></mets:eraldis><mets:eraldis><mets:katastriNr>71401:001:1256</mets:katastriNr><mets:eraldiseNr>6</mets:eraldiseNr><mets:inventKuup>2018-12-10+02:00</mets:inventKuup><mets:vKood>714</mets:vKood><mets:mKood>74</mets:mKood><mets:takseerija>38403194211</mets:takseerija><mets:pindala>0.25</mets:pindala><mets:kuivendatud>0</mets:kuivendatud><mets:kasvukoht>KL</mets:kasvukoht><mets:peapuuliik>MA</mets:peapuuliik><mets:korgusIndeks>18.2</mets:korgusIndeks><mets:boniteet>4</mets:boniteet><mets:tuleohuklass>1</mets:tuleohuklass><mets:arenguklass>K</mets:arenguklass><mets:kkVanus>72</mets:kkVanus><mets:kkRaievanus>110</mets:kkRaievanus><mets:juurdekasv>3.5</mets:juurdekasv><mets:rPindala1>17.9</mets:rPindala1><mets:taius1>58</mets:taius1><mets:tagavara1Ha>131</mets:tagavara1Ha><mets:tagavaraYHa>0</mets:tagavaraYHa><mets:geomeetria srsName="EPSG:3301"><gml:polygonMember xlink:type="simple"><gml:Polygon><gml:outerBoundaryIs><gml:LinearRing><gml:coordinates>395025.2508742843,6486894.980463851 395030.83,6486917.48 395007.7,6486926.37 394973.23,6486949.35 394988.49,6486957.49 395036.06583491,6486953.518254689 395061.35,6486905.62 395039.79,6486894.11 395025.2508742843,6486894.980463851</gml:coordinates></gml:LinearRing></gml:outerBoundaryIs></gml:Polygon></gml:polygonMember></mets:geomeetria><mets:elemendid><mets:element><mets:rinne>1</mets:rinne><mets:puuliik>MA</mets:puuliik><mets:paritolu>S</mets:paritolu><mets:osakaal>100</mets:osakaal><mets:vanus>65</mets:vanus><mets:synniaasta>1953</mets:synniaasta><mets:korgus>14.0</mets:korgus><mets:diameeter>22</mets:diameeter><mets:rinnaspindala>17.9</mets:rinnaspindala><mets:tagavara>131</mets:tagavara><mets:arv>470</mets:arv><mets:enamus>1</mets:enamus></mets:element></mets:elemendid><mets:isearasused><mets:isearasus>AO</mets:isearasus></mets:isearasused><mets:tood><mets:too><mets:too>HR</mets:too><mets:jarjekord>8</mets:jarjekord><mets:tooAasta>2018</mets:tooAasta></mets:too></mets:tood></mets:eraldis></mets:eraldised></mets:yksus></mets:yksused></mets:eraldisEsitamineRequest>